{
  "channeldata": {
    "activate.d": false,
    "binary_prefix": false,
    "deactivate.d": false,
    "description": null,
    "dev_url": null,
    "doc_source_url": null,
    "doc_url": null,
    "home": "http://openturns.org/",
    "icon_hash": null,
    "icon_url": null,
    "identifiers": null,
    "keywords": null,
    "license": "LGPL3",
    "post_link": false,
    "pre_link": false,
    "pre_unlink": false,
    "recipe_origin": null,
    "run_exports": {},
    "source_git_url": null,
    "source_url": "https://github.com/openturns/build/releases/download/v1.9rc1/openturns-1.9rc1-py3.6-x86_64.exe",
    "subdirs": [
      "win-64"
    ],
    "summary": "Uncertainty treatment library",
    "tags": null,
    "text_prefix": true,
    "timestamp": 0,
    "version": "1.9rc1"
  },
  "channeldata_version": 1,
  "feedstock": null,
  "labels": [
    "main",
    "cf202003"
  ],
  "package": "openturns-1.9rc1-py36_202.tar.bz2",
  "repodata": {
    "build": "py36_202",
    "build_number": 202,
    "depends": [
      "python 3.6*",
      "python >=3.6.1"
    ],
    "license": "LGPL3",
    "md5": "8e8fc6e1933f93585c47065ddf3012cb",
    "name": "openturns",
    "sha256": "91c878ba1126cc6a5adb11482e3647ed8be45b7d01a87d65a7eb66967ae35779",
    "size": 57155369,
    "subdir": "win-64",
    "version": "1.9rc1"
  },
  "repodata_version": 1,
  "subdir": "win-64",
  "url": "https://conda.anaconda.org/conda-forge/win-64/openturns-1.9rc1-py36_202.tar.bz2"
}