{
  "channeldata": {
    "activate.d": false,
    "binary_prefix": false,
    "deactivate.d": false,
    "description": null,
    "dev_url": "https://github.com/embotech/ecos-python",
    "doc_source_url": null,
    "doc_url": null,
    "home": "https://github.com/embotech/ecos",
    "icon_hash": null,
    "icon_url": null,
    "identifiers": null,
    "keywords": null,
    "license": "GPL-3.0-only",
    "post_link": false,
    "pre_link": false,
    "pre_unlink": false,
    "recipe_origin": null,
    "run_exports": {},
    "source_git_url": null,
    "source_url": null,
    "subdirs": [
      "osx-arm64"
    ],
    "summary": "Python interface for ECOS, a lightweight conic solver for second-order cone programming",
    "tags": null,
    "text_prefix": false,
    "timestamp": 1641336706,
    "version": "2.0.9"
  },
  "channeldata_version": 1,
  "feedstock": "ecos-feedstock",
  "labels": [
    "main"
  ],
  "package": "ecos-2.0.9-py310h949c51b_0.tar.bz2",
  "repodata": {
    "build": "py310h949c51b_0",
    "build_number": 0,
    "depends": [
      "numpy >=1.21.5,<2.0a0",
      "python >=3.10,<3.11.0a0",
      "python >=3.10,<3.11.0a0 *_cpython",
      "python_abi 3.10.* *_cp310",
      "scipy >=1.1"
    ],
    "license": "GPL-3.0-only",
    "license_family": "GPL",
    "md5": "9a2f8a56fc8802994300bc147c148de9",
    "name": "ecos",
    "sha256": "2b01cda5af2c448e8c88f9ab5cf432b686dee8eb1f7e525ba32ea430b3755447",
    "size": 83937,
    "subdir": "osx-arm64",
    "timestamp": 1641336706351,
    "version": "2.0.9"
  },
  "repodata_version": 1,
  "subdir": "osx-arm64",
  "url": "https://github.com/conda-forge/releases/releases/download/osx-arm64/ecos-2.0.9-py310h949c51b_0.tar.bz2/ecos-2.0.9-py310h949c51b_0.tar.bz2"
}