{
  "channeldata": {
    "activate.d": false,
    "binary_prefix": true,
    "deactivate.d": false,
    "description": null,
    "dev_url": null,
    "doc_source_url": null,
    "doc_url": null,
    "home": "https://github.com/ignitionrobotics/ign-transport",
    "icon_hash": null,
    "icon_url": null,
    "identifiers": null,
    "keywords": null,
    "license": "Apache-2.0",
    "post_link": false,
    "pre_link": false,
    "pre_unlink": false,
    "recipe_origin": null,
    "run_exports": {
      "9.1.0": {
        "weak": [
          "libignition-transport9 >=9.1.0,<10.0a0"
        ]
      }
    },
    "source_git_url": null,
    "source_url": null,
    "subdirs": [
      "linux-aarch64"
    ],
    "summary": "Ignition Transport",
    "tags": null,
    "text_prefix": true,
    "timestamp": 1624783827,
    "version": "9.1.0"
  },
  "channeldata_version": 1,
  "feedstock": "libignition-transport4-feedstock",
  "labels": [
    "main"
  ],
  "package": "libignition-transport9-9.1.0-h10f5916_5.tar.bz2",
  "repodata": {
    "build": "h10f5916_5",
    "build_number": 5,
    "depends": [
      "cppzmq",
      "libgcc-ng >=9.3.0",
      "libignition-cmake2 >=2.8.0,<3.0a0",
      "libignition-msgs6 >=6.4.0,<7.0a0",
      "libignition-tools1 >=1.2.0,<2.0a0",
      "libprotobuf >=3.16.0,<3.17.0a0",
      "libstdcxx-ng >=9.3.0",
      "libuuid >=2.32.1,<3.0a0",
      "sqlite >=3.36.0,<4.0a0",
      "zeromq >=4.3.4,<4.4.0a0"
    ],
    "license": "Apache-2.0",
    "md5": "4298ade7a4486ef2b90def7cfb9e8c65",
    "name": "libignition-transport9",
    "sha256": "40c81b41b4e6c5257c8e29254fdb9d06f632d532a6d963fda0b4c8ace9e1206f",
    "size": 492229,
    "subdir": "linux-aarch64",
    "timestamp": 1624783827579,
    "version": "9.1.0"
  },
  "repodata_version": 1,
  "subdir": "linux-aarch64",
  "url": "https://github.com/conda-forge/releases/releases/download/linux-aarch64/libignition-transport9-9.1.0-h10f5916_5.tar.bz2/libignition-transport9-9.1.0-h10f5916_5.tar.bz2"
}