{
  "channeldata": {
    "activate.d": false,
    "binary_prefix": false,
    "deactivate.d": false,
    "description": "Control ITT's IDL (Interactive Data Language) from within Python",
    "dev_url": null,
    "doc_source_url": null,
    "doc_url": null,
    "home": "https://github.com/anthonyjsmith/pIDLy",
    "icon_hash": null,
    "icon_url": null,
    "identifiers": null,
    "keywords": null,
    "license": "MIT",
    "post_link": false,
    "pre_link": false,
    "pre_unlink": false,
    "recipe_origin": null,
    "run_exports": {},
    "source_git_url": null,
    "source_url": "https://pypi.io/packages/source/p/pIDLy/pIDLy-0.2.7.tar.gz",
    "subdirs": [
      "osx-64"
    ],
    "summary": "IDL within Python",
    "tags": null,
    "text_prefix": false,
    "timestamp": 1611334199,
    "version": "0.2.7"
  },
  "channeldata_version": 1,
  "feedstock": null,
  "labels": [
    "main"
  ],
  "package": "pidly-0.2.7-py36h79c6626_1002.tar.bz2",
  "repodata": {
    "build": "py36h79c6626_1002",
    "build_number": 1002,
    "depends": [
      "numpy",
      "pexpect",
      "python >=3.6,<3.7.0a0",
      "python_abi 3.6.* *_cp36m",
      "scipy"
    ],
    "license": "MIT",
    "license_family": "MIT",
    "md5": "18a0934c5205edee7ec4348240efd8e1",
    "name": "pidly",
    "sha256": "7fd519fc9023cc5acbdff124e08be0e2179ee809a4d2ca558b9f15549f3593ca",
    "size": 29120,
    "subdir": "osx-64",
    "timestamp": 1611334199965,
    "version": "0.2.7"
  },
  "repodata_version": 1,
  "subdir": "osx-64",
  "url": "https://conda.anaconda.org/conda-forge/osx-64/pidly-0.2.7-py36h79c6626_1002.tar.bz2"
}