{
  "channeldata": {
    "activate.d": false,
    "binary_prefix": false,
    "deactivate.d": false,
    "description": null,
    "dev_url": "https://github.com/explosion/srsly",
    "doc_source_url": null,
    "doc_url": "https://github.com/explosion/srsly",
    "home": "http://github.com/explosion/srsly",
    "icon_hash": null,
    "icon_url": null,
    "identifiers": null,
    "keywords": null,
    "license": "MIT",
    "post_link": false,
    "pre_link": false,
    "pre_unlink": false,
    "recipe_origin": null,
    "run_exports": {},
    "source_git_url": null,
    "source_url": "https://pypi.io/packages/source/s/srsly/srsly-2.3.0.tar.gz",
    "subdirs": [
      "linux-ppc64le"
    ],
    "summary": "Modern high-performance serialization utilities for Python",
    "tags": null,
    "text_prefix": false,
    "timestamp": 1601998974,
    "version": "2.3.0"
  },
  "channeldata_version": 1,
  "feedstock": "srsly-feedstock",
  "labels": [
    "main"
  ],
  "package": "srsly-2.3.0-py36hd724563_1.tar.bz2",
  "repodata": {
    "build": "py36hd724563_1",
    "build_number": 1,
    "depends": [
      "libgcc-ng >=8.4.0",
      "libstdcxx-ng >=8.4.0",
      "python >=3.6,<3.7.0a0",
      "python_abi 3.6.* *_cp36m"
    ],
    "license": "MIT",
    "license_family": "MIT",
    "md5": "eb4948b5ece48b5d442574902b02f891",
    "name": "srsly",
    "sha256": "011ab3b220af2ea476f6fbe22986ed4d27584ed124fd38ddb4386a2d556e610c",
    "size": 551774,
    "subdir": "linux-ppc64le",
    "timestamp": 1601998974561,
    "version": "2.3.0"
  },
  "repodata_version": 1,
  "subdir": "linux-ppc64le",
  "url": "https://github.com/regro/releases/releases/download/linux-ppc64le/srsly-2.3.0-py36hd724563_1.tar.bz2/srsly-2.3.0-py36hd724563_1.tar.bz2"
}