{
  "channeldata": {
    "activate.d": false,
    "binary_prefix": false,
    "deactivate.d": false,
    "description": null,
    "dev_url": "https://github.com/davidbrochart/ipyx",
    "doc_source_url": null,
    "doc_url": "https://github.com/davidbrochart/ipyx",
    "home": "https://github.com/davidbrochart/ipyx",
    "icon_hash": null,
    "icon_url": null,
    "identifiers": null,
    "keywords": null,
    "license": "BSD-3-Clause",
    "post_link": false,
    "pre_link": false,
    "pre_unlink": false,
    "recipe_origin": null,
    "run_exports": {},
    "source_git_url": null,
    "source_url": "https://pypi.io/packages/source/i/ipyx/ipyx-0.1.0.tar.gz",
    "subdirs": [
      "noarch"
    ],
    "summary": "A Jupyter widget library for reactive variables",
    "tags": null,
    "text_prefix": false,
    "timestamp": 1621612021,
    "version": "0.1.0"
  },
  "channeldata_version": 1,
  "feedstock": "ipyx-feedstock",
  "labels": [
    "main"
  ],
  "package": "ipyx-0.1.0-pyhd8ed1ab_0.tar.bz2",
  "repodata": {
    "build": "pyhd8ed1ab_0",
    "build_number": 0,
    "depends": [
      "ipywidgets >=7.0.0",
      "python >=3.6"
    ],
    "license": "BSD-3-Clause",
    "license_family": "BSD",
    "md5": "b82f7a886010c1fa347e4f91dbca5494",
    "name": "ipyx",
    "noarch": "python",
    "sha256": "1a19c98a6aaff83e94682a86052e454835fd1de5d32a613188269c109ccb60d1",
    "size": 31099,
    "subdir": "noarch",
    "timestamp": 1621612021527,
    "version": "0.1.0"
  },
  "repodata_version": 1,
  "subdir": "noarch",
  "url": "https://github.com/conda-forge/releases/releases/download/noarch/ipyx-0.1.0-pyhd8ed1ab_0.tar.bz2/ipyx-0.1.0-pyhd8ed1ab_0.tar.bz2"
}