{
  "channeldata": {
    "activate.d": false,
    "binary_prefix": false,
    "deactivate.d": false,
    "description": null,
    "dev_url": "https://bitbucket.org/incitron/miningpy",
    "doc_source_url": null,
    "doc_url": "https://miningpy.readthedocs.io",
    "home": "https://pypi.org/project/miningpy/",
    "icon_hash": null,
    "icon_url": null,
    "identifiers": null,
    "keywords": null,
    "license": "MIT",
    "post_link": false,
    "pre_link": false,
    "pre_unlink": false,
    "recipe_origin": null,
    "run_exports": {},
    "source_git_url": null,
    "source_url": "https://pypi.io/packages/source/m/miningpy/miningpy-0.2.0.tar.gz",
    "subdirs": [
      "win-64"
    ],
    "summary": "python tools for mining engineering",
    "tags": null,
    "text_prefix": false,
    "timestamp": 1598656305,
    "version": "0.2.0"
  },
  "channeldata_version": 1,
  "feedstock": null,
  "labels": [
    "main"
  ],
  "package": "miningpy-0.2.0-py38h32f6830_1.tar.bz2",
  "repodata": {
    "build": "py38h32f6830_1",
    "build_number": 1,
    "depends": [
      "ezdxf >=0.13.1",
      "matplotlib-base",
      "numpy",
      "pandas",
      "python >=3.8,<3.9.0a0",
      "python_abi 3.8.* *_cp38",
      "pyvista",
      "vtk >=8.0"
    ],
    "license": "MIT",
    "md5": "b21471012a138c9b582494fc91933cfb",
    "name": "miningpy",
    "sha256": "96f96f2d88fee407f06333a8b5727f24efba87d8b565e2d0db30137057485001",
    "size": 1483712,
    "subdir": "win-64",
    "timestamp": 1598656305722,
    "version": "0.2.0"
  },
  "repodata_version": 1,
  "subdir": "win-64",
  "url": "https://github.com/regro/releases/releases/download/win-64/miningpy-0.2.0-py38h32f6830_1.tar.bz2/miningpy-0.2.0-py38h32f6830_1.tar.bz2"
}