{
  "channeldata": {
    "activate.d": false,
    "binary_prefix": false,
    "deactivate.d": false,
    "description": "The ItemAdapter class is a wrapper for data container objects, providing a common interface to handle objects of different types in an uniform manner, regardless of their underlying implementation.",
    "dev_url": null,
    "doc_source_url": null,
    "doc_url": null,
    "home": "https://github.com/scrapy/itemadapter",
    "icon_hash": null,
    "icon_url": null,
    "identifiers": null,
    "keywords": null,
    "license": "BSD-3-Clause",
    "post_link": false,
    "pre_link": false,
    "pre_unlink": false,
    "recipe_origin": null,
    "run_exports": {},
    "source_git_url": null,
    "source_url": "https://pypi.io/packages/source/i/itemadapter/itemadapter-0.6.0.tar.gz",
    "subdirs": [
      "noarch"
    ],
    "summary": "Common interface for different data containers",
    "tags": null,
    "text_prefix": false,
    "timestamp": 1652457271,
    "version": "0.6.0"
  },
  "channeldata_version": 1,
  "feedstock": "itemadapter-feedstock",
  "labels": [
    "main"
  ],
  "package": "itemadapter-0.6.0-pyhd8ed1ab_0.tar.bz2",
  "repodata": {
    "build": "pyhd8ed1ab_0",
    "build_number": 0,
    "depends": [
      "python >=3.5"
    ],
    "license": "BSD-3-Clause",
    "license_family": "BSD",
    "md5": "cc67230328f38d0df939d5066e853763",
    "name": "itemadapter",
    "noarch": "python",
    "sha256": "3decd00718f15413689faa0155e437c11910838fa61788ade6a892fae22a4088",
    "size": 13787,
    "subdir": "noarch",
    "timestamp": 1652457271166,
    "version": "0.6.0"
  },
  "repodata_version": 1,
  "subdir": "noarch",
  "url": "https://github.com/conda-forge/releases/releases/download/noarch/itemadapter-0.6.0-pyhd8ed1ab_0.tar.bz2/itemadapter-0.6.0-pyhd8ed1ab_0.tar.bz2"
}