{
  "channeldata": {
    "activate.d": false,
    "binary_prefix": false,
    "deactivate.d": false,
    "description": null,
    "dev_url": null,
    "doc_source_url": null,
    "doc_url": null,
    "home": "https://github.com/dotnet/desktop",
    "icon_hash": null,
    "icon_url": null,
    "identifiers": null,
    "keywords": null,
    "license": "MIT",
    "post_link": false,
    "pre_link": false,
    "pre_unlink": false,
    "recipe_origin": null,
    "run_exports": {},
    "source_git_url": null,
    "source_url": "https://dotnetcli.azureedge.net/dotnet/Sdk/3.1.408/dotnet-sdk-3.1.408-win-x64.zip",
    "subdirs": [
      "win-64"
    ],
    "summary": ".NET Core is a free and open-source managed computer software framework for the Windows, Linux, and macOS operating systems.",
    "tags": null,
    "text_prefix": false,
    "timestamp": 1619094617,
    "version": "3.1.14"
  },
  "channeldata_version": 1,
  "feedstock": "dotnet-feedstock",
  "labels": [
    "main"
  ],
  "package": "dotnet-desktop-3.1.14-h57928b3_2.tar.bz2",
  "repodata": {
    "build": "h57928b3_2",
    "build_number": 2,
    "depends": [
      "dotnet-runtime 3.1.14.*"
    ],
    "license": "MIT",
    "md5": "3fd1c75f0c827cc1f392f8c235f805fc",
    "name": "dotnet-desktop",
    "sha256": "50f094675bad26c7a45049173e92403d190dde5c2538d6d95e72a5fefdf7c7da",
    "size": 32132911,
    "subdir": "win-64",
    "timestamp": 1619094617302,
    "version": "3.1.14"
  },
  "repodata_version": 1,
  "subdir": "win-64",
  "url": "https://github.com/conda-forge/releases/releases/download/win-64/dotnet-desktop-3.1.14-h57928b3_2.tar.bz2/dotnet-desktop-3.1.14-h57928b3_2.tar.bz2"
}