{
  "channeldata": {
    "activate.d": false,
    "binary_prefix": false,
    "deactivate.d": false,
    "description": "The Earth Engine Python API allows developers to interact with Google Earth Engine, a web platform for global scale geospatial analysis.",
    "dev_url": "https://github.com/google/earthengine-api/",
    "doc_source_url": null,
    "doc_url": "https://developers.google.com/earth-engine/",
    "home": "https://earthengine.google.com/",
    "icon_hash": null,
    "icon_url": null,
    "identifiers": null,
    "keywords": null,
    "license": "Apache-2.0",
    "post_link": false,
    "pre_link": false,
    "pre_unlink": false,
    "recipe_origin": null,
    "run_exports": {},
    "source_git_url": null,
    "source_url": "https://pypi.io/packages/source/e/earthengine-api/earthengine-api-0.1.150.tar.gz",
    "subdirs": [
      "noarch"
    ],
    "summary": "Earth Engine Python API",
    "tags": null,
    "text_prefix": false,
    "timestamp": 1538019794,
    "version": "0.1.150"
  },
  "channeldata_version": 1,
  "feedstock": null,
  "labels": [
    "main",
    "cf202003",
    "cf201901"
  ],
  "package": "earthengine-api-0.1.150-py_0.tar.bz2",
  "repodata": {
    "build": "py_0",
    "build_number": 0,
    "depends": [
      "google-api-python-client",
      "pyopenssl >=0.11",
      "python"
    ],
    "license": "Apache-2.0",
    "license_family": "APACHE",
    "md5": "a664fbd96f3dfcf248fc45ee16a2b05e",
    "name": "earthengine-api",
    "noarch": "python",
    "sha256": "cddf136defaa7e29540c8268cb1c1b883a22ca78d9ce115e6492932fcdc84655",
    "size": 91626,
    "subdir": "noarch",
    "timestamp": 1538019794217,
    "version": "0.1.150"
  },
  "repodata_version": 1,
  "subdir": "noarch",
  "url": "https://github.com/regro/releases/releases/download/noarch/earthengine-api-0.1.150-py_0.tar.bz2/earthengine-api-0.1.150-py_0.tar.bz2"
}