{
  "channeldata": {
    "activate.d": false,
    "binary_prefix": false,
    "deactivate.d": false,
    "description": null,
    "dev_url": null,
    "doc_source_url": null,
    "doc_url": null,
    "home": "https://github.com/jupyterhub/jupyterhub",
    "icon_hash": null,
    "icon_url": null,
    "identifiers": null,
    "keywords": null,
    "license": "BSD-3-Clause",
    "post_link": false,
    "pre_link": false,
    "pre_unlink": false,
    "recipe_origin": null,
    "run_exports": {},
    "source_git_url": null,
    "source_url": "https://pypi.io/packages/source/j/jupyterhub/jupyterhub-1.4.1.tar.gz",
    "subdirs": [
      "osx-64"
    ],
    "summary": "Multi-user server for Jupyter notebooks",
    "tags": null,
    "text_prefix": false,
    "timestamp": 1621023790,
    "version": "1.4.1"
  },
  "channeldata_version": 1,
  "feedstock": "jupyterhub-feedstock",
  "labels": [
    "main"
  ],
  "package": "jupyterhub-singleuser-1.4.1-py38h50d1736_0.tar.bz2",
  "repodata": {
    "build": "py38h50d1736_0",
    "build_number": 0,
    "depends": [
      "jupyterhub-base 1.4.1 py38h50d1736_0",
      "notebook >=4",
      "python >=3.8,<3.9.0a0",
      "python_abi 3.8.* *_cp38"
    ],
    "license": "BSD-3-Clause",
    "md5": "8c8b094632a67e18f036dda9f3d007f0",
    "name": "jupyterhub-singleuser",
    "sha256": "7a9a334af0dcc7c4560494582ea9f60b2f7a97741052cdb6c260f0971b802192",
    "size": 4821,
    "subdir": "osx-64",
    "timestamp": 1621023790814,
    "version": "1.4.1"
  },
  "repodata_version": 1,
  "subdir": "osx-64",
  "url": "https://github.com/conda-forge/releases/releases/download/osx-64/jupyterhub-singleuser-1.4.1-py38h50d1736_0.tar.bz2/jupyterhub-singleuser-1.4.1-py38h50d1736_0.tar.bz2"
}