{
  "channeldata": {
    "activate.d": false,
    "binary_prefix": false,
    "deactivate.d": false,
    "description": null,
    "dev_url": null,
    "doc_source_url": null,
    "doc_url": null,
    "home": "https://CRAN.R-project.org/package=GFA",
    "icon_hash": null,
    "icon_url": null,
    "identifiers": null,
    "keywords": null,
    "license": "MIT",
    "post_link": false,
    "pre_link": false,
    "pre_unlink": false,
    "recipe_origin": null,
    "run_exports": {},
    "source_git_url": null,
    "source_url": [
      "https://cran.r-project.org/src/contrib/Archive/GFA/GFA_1.0.3.tar.gz",
      "https://cran.r-project.org/src/contrib/GFA_1.0.3.tar.gz"
    ],
    "subdirs": [
      "noarch"
    ],
    "summary": "Factor analysis implementation for multiple data sources, i.e., for groups of variables. The whole data analysis pipeline is provided, including functions and recommendations for data normalization and model definition, as well as missing value prediction and model visualization. The model group factor analysis (GFA) is inferred with Gibbs sampling, and it has been presented originally by Virtanen et al. (2012), and extended in Klami et al. (2015) <DOI:10.1109/TNNLS.2014.2376974> and Bunte et al. (2016) <DOI:10.1093/bioinformatics/btw207>; for details, see the citation info.",
    "tags": null,
    "text_prefix": false,
    "timestamp": 1563698505,
    "version": "1.0.3"
  },
  "channeldata_version": 1,
  "feedstock": null,
  "labels": [
    "main",
    "cf202003"
  ],
  "package": "r-gfa-1.0.3-r36h6115d3f_1001.tar.bz2",
  "repodata": {
    "build": "r36h6115d3f_1001",
    "build_number": 1001,
    "depends": [
      "r-base >=3.6,<3.7.0a0"
    ],
    "license": "MIT",
    "license_family": "MIT",
    "md5": "c8f056e41389f584fca1e871c242bbba",
    "name": "r-gfa",
    "noarch": "generic",
    "sha256": "d44f89b15320b8f29aea6e7ef4263d40e817feb116fe4cc94dcfdb4f799d1bc8",
    "size": 162166,
    "subdir": "noarch",
    "timestamp": 1563698505790,
    "version": "1.0.3"
  },
  "repodata_version": 1,
  "subdir": "noarch",
  "url": "https://conda.anaconda.org/conda-forge/noarch/r-gfa-1.0.3-r36h6115d3f_1001.tar.bz2"
}