{
  "channeldata": {
    "activate.d": false,
    "binary_prefix": false,
    "deactivate.d": false,
    "description": null,
    "dev_url": null,
    "doc_source_url": null,
    "doc_url": null,
    "home": "https://github.com/tmpvar/jsdom",
    "icon_hash": null,
    "icon_url": null,
    "identifiers": null,
    "keywords": null,
    "license": "MIT",
    "post_link": false,
    "pre_link": false,
    "pre_unlink": false,
    "recipe_origin": null,
    "run_exports": {},
    "source_git_url": null,
    "source_url": "https://github.com/tmpvar/jsdom/archive/11.0.0.tar.gz",
    "subdirs": [
      "osx-64"
    ],
    "summary": "jsdom is a pure-JavaScript implementation of many web standards, notably the WHATWG DOM and HTML Standards, for use with Node.js",
    "tags": null,
    "text_prefix": true,
    "timestamp": 0,
    "version": "11.0.0"
  },
  "channeldata_version": 1,
  "feedstock": null,
  "labels": [
    "main",
    "cf202003"
  ],
  "package": "jsdom-11.0.0-0.tar.bz2",
  "repodata": {
    "build": "0",
    "build_number": 0,
    "depends": [
      "nodejs 6.*"
    ],
    "license": "MIT",
    "md5": "7bb52deed1e1cc3c33ea5330a4060992",
    "name": "jsdom",
    "sha256": "1ef5dccb15952d47b4f53cbc82f00db861794a939a4d83cee71e08624ea13d6c",
    "size": 2485423,
    "subdir": "osx-64",
    "version": "11.0.0"
  },
  "repodata_version": 1,
  "subdir": "osx-64",
  "url": "https://conda.anaconda.org/conda-forge/osx-64/jsdom-11.0.0-0.tar.bz2"
}