{
  "channeldata": {
    "activate.d": false,
    "binary_prefix": false,
    "deactivate.d": false,
    "description": null,
    "dev_url": null,
    "doc_source_url": null,
    "doc_url": null,
    "home": "https://code.zmaw.de/projects/cdo",
    "icon_hash": null,
    "icon_url": null,
    "identifiers": null,
    "keywords": null,
    "license": "GPL-2.0",
    "post_link": false,
    "pre_link": false,
    "pre_unlink": false,
    "recipe_origin": null,
    "run_exports": {},
    "source_git_url": null,
    "source_url": "https://code.zmaw.de/attachments/download/16035/cdo-1.9.2.tar.gz",
    "subdirs": [
      "osx-64"
    ],
    "summary": "CLI tools to manipulate and analyse Climate and NWP model Data.",
    "tags": null,
    "text_prefix": false,
    "timestamp": 0,
    "version": "1.9.2"
  },
  "channeldata_version": 1,
  "feedstock": null,
  "labels": [
    "cf201901"
  ],
  "package": "cdo-1.9.2-0.tar.bz2",
  "repodata": {
    "build": "0",
    "build_number": 0,
    "depends": [
      "eccodes",
      "fftw",
      "jasper",
      "libnetcdf 4.4.*",
      "libxml2 2.9.*",
      "proj4 4.9.3",
      "udunits2"
    ],
    "license": "GPL-2.0",
    "md5": "6f7fbcef0637c427125a1bf2ccd23b1f",
    "name": "cdo",
    "sha256": "9ce8913a2628fb7c591fcbbf850841a7ce88838bc09fe35960100f19424f7e08",
    "size": 2503805,
    "subdir": "osx-64",
    "version": "1.9.2"
  },
  "repodata_version": 1,
  "subdir": "osx-64",
  "url": "https://conda.anaconda.org/conda-forge/label/cf201901/osx-64/cdo-1.9.2-0.tar.bz2"
}