{
  "channeldata": {
    "activate.d": false,
    "binary_prefix": false,
    "deactivate.d": false,
    "description": "A CPython extension module to access Cling through cppyy-backend.",
    "dev_url": "https://bitbucket.org/wlav/cpycppyy/src",
    "doc_source_url": null,
    "doc_url": "http://cppyy.readthedocs.io/",
    "home": "https://pypi.org/project/CPyCppyy/",
    "icon_hash": null,
    "icon_url": null,
    "identifiers": null,
    "keywords": null,
    "license": "BSD-3-Clause",
    "post_link": false,
    "pre_link": false,
    "pre_unlink": false,
    "recipe_origin": null,
    "run_exports": {},
    "source_git_url": null,
    "source_url": "https://pypi.io/packages/source/c/cpycppyy/CPyCppyy-1.9.3.tar.gz",
    "subdirs": [
      "linux-64"
    ],
    "summary": "CPython-C++ bindings interface based on Cling/LLVM",
    "tags": null,
    "text_prefix": false,
    "timestamp": 1568623726,
    "version": "1.9.3"
  },
  "channeldata_version": 1,
  "feedstock": null,
  "labels": [
    "cf202003",
    "main"
  ],
  "package": "cpycppyy-1.9.3-py27hc9558a2_0.tar.bz2",
  "repodata": {
    "build": "py27hc9558a2_0",
    "build_number": 0,
    "depends": [
      "cppyy-backend",
      "libgcc-ng >=7.3.0",
      "libstdcxx-ng >=7.3.0",
      "python >=2.7,<2.8.0a0"
    ],
    "license": "BSD-3-Clause",
    "license_family": "BSD",
    "md5": "b75558224371cb6f3a88dcc99336dc13",
    "name": "cpycppyy",
    "sha256": "8506e56828c44824f691497eb230b05d53c4785e95070961dd24cf056317199c",
    "size": 250847,
    "subdir": "linux-64",
    "timestamp": 1568623726936,
    "version": "1.9.3"
  },
  "repodata_version": 1,
  "subdir": "linux-64",
  "url": "https://conda.anaconda.org/conda-forge/linux-64/cpycppyy-1.9.3-py27hc9558a2_0.tar.bz2"
}