{
  "channeldata": {
    "activate.d": false,
    "binary_prefix": false,
    "deactivate.d": false,
    "description": null,
    "dev_url": null,
    "doc_source_url": null,
    "doc_url": null,
    "home": "https://github.com/alexmojaki/heartrate",
    "icon_hash": null,
    "icon_url": null,
    "identifiers": null,
    "keywords": null,
    "license": "MIT",
    "post_link": false,
    "pre_link": false,
    "pre_unlink": false,
    "recipe_origin": null,
    "run_exports": {},
    "source_git_url": null,
    "source_url": "https://pypi.io/packages/source/h/heartrate/heartrate-0.2.2.tar.gz",
    "subdirs": [
      "noarch"
    ],
    "summary": "Simple real time visualisation of the execution of a Python program.",
    "tags": null,
    "text_prefix": false,
    "timestamp": 1636825085,
    "version": "0.2.2"
  },
  "channeldata_version": 1,
  "feedstock": "heartrate-feedstock",
  "labels": [
    "main"
  ],
  "package": "heartrate-0.2.2-pyhd8ed1ab_0.tar.bz2",
  "repodata": {
    "build": "pyhd8ed1ab_0",
    "build_number": 0,
    "depends": [
      "asttokens",
      "executing",
      "flask",
      "pygments",
      "python >=3.6"
    ],
    "license": "MIT",
    "md5": "dd9551fde3753134f6833b6693b95143",
    "name": "heartrate",
    "noarch": "python",
    "sha256": "cb66537b28079440bc32030c75ae59de931180fc60674e9ae55e03adccb84efe",
    "size": 233566,
    "subdir": "noarch",
    "timestamp": 1636825085506,
    "version": "0.2.2"
  },
  "repodata_version": 1,
  "subdir": "noarch",
  "url": "https://github.com/conda-forge/releases/releases/download/noarch/heartrate-0.2.2-pyhd8ed1ab_0.tar.bz2/heartrate-0.2.2-pyhd8ed1ab_0.tar.bz2"
}