{
  "channeldata": {
    "activate.d": false,
    "binary_prefix": false,
    "deactivate.d": false,
    "description": null,
    "dev_url": null,
    "doc_source_url": null,
    "doc_url": null,
    "home": "http://urwid.org/",
    "icon_hash": null,
    "icon_url": null,
    "identifiers": null,
    "keywords": null,
    "license": "LGPL-2.1-or-later",
    "post_link": false,
    "pre_link": false,
    "pre_unlink": false,
    "recipe_origin": null,
    "run_exports": {},
    "source_git_url": null,
    "source_url": "https://pypi.io/packages/source/u/urwid/urwid-2.1.2.tar.gz",
    "subdirs": [
      "linux-64"
    ],
    "summary": "A full-featured console (xterm et al.) user interface library",
    "tags": null,
    "text_prefix": false,
    "timestamp": 1612907961,
    "version": "2.1.2"
  },
  "channeldata_version": 1,
  "feedstock": null,
  "labels": [
    "main"
  ],
  "package": "urwid-2.1.2-py36h8f6f2f9_3.tar.bz2",
  "repodata": {
    "build": "py36h8f6f2f9_3",
    "build_number": 3,
    "depends": [
      "libgcc-ng >=9.3.0",
      "python >=3.6,<3.7.0a0",
      "python_abi 3.6.* *_cp36m"
    ],
    "license": "LGPL-2.1-or-later",
    "license_family": "LGPL",
    "md5": "124421c5c8c8be44edea14af44484d76",
    "name": "urwid",
    "sha256": "34387764bfdf4c48887d029d85eb039fa138527c68410cebeec82e488b2ce7ff",
    "size": 408645,
    "subdir": "linux-64",
    "timestamp": 1612907961113,
    "version": "2.1.2"
  },
  "repodata_version": 1,
  "subdir": "linux-64",
  "url": "https://conda.anaconda.org/conda-forge/linux-64/urwid-2.1.2-py36h8f6f2f9_3.tar.bz2"
}