{
  "channeldata": {
    "activate.d": false,
    "binary_prefix": false,
    "deactivate.d": false,
    "description": null,
    "dev_url": "https://github.com/agronholm/apscheduler",
    "doc_source_url": null,
    "doc_url": "https://apscheduler.readthedocs.io",
    "home": "https://github.com/agronholm/apscheduler",
    "icon_hash": null,
    "icon_url": null,
    "identifiers": null,
    "keywords": null,
    "license": "MIT",
    "post_link": false,
    "pre_link": false,
    "pre_unlink": false,
    "recipe_origin": null,
    "run_exports": {},
    "source_git_url": null,
    "source_url": "https://pypi.io/packages/source/A/APScheduler/APScheduler-3.5.3.tar.gz",
    "subdirs": [
      "win-64"
    ],
    "summary": "In-process task scheduler with Cron-like capabilities",
    "tags": null,
    "text_prefix": false,
    "timestamp": 1534336948,
    "version": "3.5.3"
  },
  "channeldata_version": 1,
  "feedstock": null,
  "labels": [
    "main",
    "cf202003",
    "cf201901"
  ],
  "package": "apscheduler-3.5.3-py36_0.tar.bz2",
  "repodata": {
    "build": "py36_0",
    "build_number": 0,
    "depends": [
      "python >=3.6,<3.7.0a0",
      "pytz",
      "setuptools",
      "six >=1.4.0",
      "tzlocal >=1.2"
    ],
    "license": "MIT",
    "md5": "7068da7713a8bb0e1a9085ddf9923a02",
    "name": "apscheduler",
    "sha256": "af0038fbce4b5a4a5fccc01a35501df88e53272a4ea305d401b460887a2f066e",
    "size": 78842,
    "subdir": "win-64",
    "timestamp": 1534336948514,
    "version": "3.5.3"
  },
  "repodata_version": 1,
  "subdir": "win-64",
  "url": "https://github.com/regro/releases/releases/download/win-64/apscheduler-3.5.3-py36_0.tar.bz2/apscheduler-3.5.3-py36_0.tar.bz2"
}