{
  "channeldata": {
    "activate.d": false,
    "binary_prefix": false,
    "deactivate.d": false,
    "description": null,
    "dev_url": null,
    "doc_source_url": null,
    "doc_url": null,
    "home": "http://openturns.org/",
    "icon_hash": null,
    "icon_url": null,
    "identifiers": null,
    "keywords": null,
    "license": "LGPL3",
    "post_link": false,
    "pre_link": false,
    "pre_unlink": false,
    "recipe_origin": null,
    "run_exports": {},
    "source_git_url": null,
    "source_url": "https://github.com/openturns/openturns/archive/v1.12rc1.tar.gz",
    "subdirs": [
      "win-64"
    ],
    "summary": "Uncertainty treatment library",
    "tags": null,
    "text_prefix": true,
    "timestamp": 1540716611,
    "version": "1.12rc1"
  },
  "channeldata_version": 1,
  "feedstock": null,
  "labels": [
    "main",
    "cf202003"
  ],
  "package": "openturns-1.12rc1-py36h298d185_203.tar.bz2",
  "repodata": {
    "build": "py36h298d185_203",
    "build_number": 203,
    "depends": [
      "psutil",
      "python >=3.6,<3.7.0a0"
    ],
    "license": "LGPL3",
    "md5": "5332592a4d26836e9ccbe86486a058eb",
    "name": "openturns",
    "sha256": "3e25a80e43b9851d07c59f24cc38e13e07a5acf5bb6ac497065ec9f867132018",
    "size": 60381402,
    "subdir": "win-64",
    "timestamp": 1540716611043,
    "version": "1.12rc1"
  },
  "repodata_version": 1,
  "subdir": "win-64",
  "url": "https://conda.anaconda.org/conda-forge/win-64/openturns-1.12rc1-py36h298d185_203.tar.bz2"
}