{
  "channeldata": {
    "activate.d": true,
    "binary_prefix": false,
    "deactivate.d": true,
    "description": null,
    "dev_url": null,
    "doc_source_url": null,
    "doc_url": null,
    "home": "https://github.com/conda-forge/ctng-compiler-activation-feedstock",
    "icon_hash": null,
    "icon_url": null,
    "identifiers": null,
    "keywords": null,
    "license": "BSD-3-Clause",
    "post_link": false,
    "pre_link": false,
    "pre_unlink": false,
    "recipe_origin": null,
    "run_exports": {
      "9.4.0": {
        "strong": [
          "libgcc-ng >=9.4.0"
        ]
      }
    },
    "source_git_url": null,
    "source_url": null,
    "subdirs": [
      "linux-s390x"
    ],
    "summary": "GNU C Compiler (activation scripts)",
    "tags": null,
    "text_prefix": false,
    "timestamp": 1641562507,
    "version": "9.4.0"
  },
  "channeldata_version": 1,
  "feedstock": "ctng-compiler-activation-feedstock",
  "labels": [
    "main"
  ],
  "package": "gcc_linux-64-9.4.0-h24064ed_4.tar.bz2",
  "repodata": {
    "build": "h24064ed_4",
    "build_number": 4,
    "depends": [
      "binutils_linux-64 2.36 h78615fc_4",
      "gcc_impl_linux-64 9.4.0.*",
      "gcc_impl_linux-s390x 9.4.0.*",
      "sysroot_linux-64",
      "sysroot_linux-s390x"
    ],
    "license": "BSD-3-Clause",
    "md5": "30c2c69778eb61785c5fb36738b14cc6",
    "name": "gcc_linux-64",
    "sha256": "e61d74ae0730affcf6317ef2ef23baff4b98d418c655c821d844c2decceda2fb",
    "size": 25066,
    "subdir": "linux-s390x",
    "timestamp": 1641562507239,
    "version": "9.4.0"
  },
  "repodata_version": 1,
  "subdir": "linux-s390x",
  "url": "https://github.com/conda-forge/releases/releases/download/linux-s390x/gcc_linux-64-9.4.0-h24064ed_4.tar.bz2/gcc_linux-64-9.4.0-h24064ed_4.tar.bz2"
}